[
  {
    "id": 1,
    "imageURL": "https://avatars.githubusercontent.com/u/112485240?v=4",
    "fullName": "Merisa Beširović",
    "description": "Merisa je mentor ove grupe.",
    "location": "Novi Pazar, Serbia"
  },
  {
    "id": 2,
    "imageURL": "https://static.vecteezy.com/system/resources/thumbnails/005/544/718/small_2x/profile-icon-design-free-vector.jpg",
    "fullName": "Hamza Nicević",
    "description": "Hamza je budući web developer...",
    "location": "Novi Pazar, Serbia"
  },
  {
    "id": 3,
    "imageURL": "https://static.vecteezy.com/system/resources/thumbnails/005/544/718/small_2x/profile-icon-design-free-vector.jpg",
    "fullName": "Amin Šaćirović",
    "description": "Amin je budući web developer...",
    "location": "Novi Pazar, Serbia"
  },
  {
    "id": 4,
    "imageURL": "https://static.vecteezy.com/system/resources/thumbnails/005/544/718/small_2x/profile-icon-design-free-vector.jpg",
    "fullName": "Said Kurpejović",
    "description": "Said je budući web developer...",
    "location": "Novi Pazar, Serbia"
  },
  {
    "id": 5,
    "imageURL": "https://static.vecteezy.com/system/resources/thumbnails/005/544/718/small_2x/profile-icon-design-free-vector.jpg",
    "fullName": "Kadir Nišić",
    "description": "Kadir je budući web developer...",
    "location": "Novi Pazar, Serbia"
  },
  {
    "id": 6,
    "imageURL": "https://static.vecteezy.com/system/resources/thumbnails/005/544/718/small_2x/profile-icon-design-free-vector.jpg",
    "fullName": "Redžep Bačevac",
    "description": "Redžep je budući web developer...",
    "location": "Novi Pazar, Serbia"
  },
  {
    "id": 7,
    "imageURL": "https://static.vecteezy.com/system/resources/thumbnails/005/544/718/small_2x/profile-icon-design-free-vector.jpg",
    "fullName": "Kadir Ćorović",
    "description": "Kadir je budući web developer...",
    "location": "Novi Pazar, Serbia"
  },
  {
    "id": 8,
    "imageURL": "https://static.vecteezy.com/system/resources/thumbnails/005/544/718/small_2x/profile-icon-design-free-vector.jpg",
    "fullName": "Ajlana Šaćirović",
    "description": "Ajlana je budući web developer...",
    "location": "Novi Pazar, Serbia"
  },
  {
    "id": 9,
    "imageURL": "https://static.vecteezy.com/system/resources/thumbnails/005/544/718/small_2x/profile-icon-design-free-vector.jpg",
    "fullName": "Saima Kurpejović",
    "description": "Saima je budući web developer...",
    "location": "Novi Pazar, Serbia"
  },
  {
    "id": 10,
    "imageURL": "https://static.vecteezy.com/system/resources/thumbnails/005/544/718/small_2x/profile-icon-design-free-vector.jpg",
    "fullName": "Džanan Bjelak",
    "description": "Džanan je budući web developer...",
    "location": "Novi Pazar, Serbia"
  },
  {
    "id": 11,
    "imageURL": "https://static.vecteezy.com/system/resources/thumbnails/005/544/718/small_2x/profile-icon-design-free-vector.jpg",
    "fullName": "Stefan Profilović",
    "description": "Stefan je budući web developer...",
    "location": "Novi Pazar, Serbia"
  },
  {
    "id": 12,
    "imageURL": "https://static.vecteezy.com/system/resources/thumbnails/005/544/718/small_2x/profile-icon-design-free-vector.jpg",
    "fullName": "Amar Dervišević",
    "description": "Amar je budući web developer...",
    "location": "Novi Pazar, Serbia"
  },
  {
    "id": 13,
    "imageURL": "https://static.vecteezy.com/system/resources/thumbnails/005/544/718/small_2x/profile-icon-design-free-vector.jpg",
    "fullName": "Kerim Brahić",
    "description": "Kerim je budući web developer...",
    "location": "Novi Pazar, Serbia"
  },
  {
    "id": 14,
    "imageURL": "https://static.vecteezy.com/system/resources/thumbnails/005/544/718/small_2x/profile-icon-design-free-vector.jpg",
    "fullName": "Lejla Dupljak",
    "description": "Lejla je budući web developer...",
    "location": "Novi Pazar, Serbia"
  },
  {
    "id": 15,
    "imageURL": "https://static.vecteezy.com/system/resources/thumbnails/005/544/718/small_2x/profile-icon-design-free-vector.jpg",
    "fullName": "Tahir Bibić",
    "description": "Tahir je budući web developer...",
    "location": "Novi Pazar, Serbia"
  },
  {
    "id": 16,
    "imageURL": "https://static.vecteezy.com/system/resources/thumbnails/005/544/718/small_2x/profile-icon-design-free-vector.jpg",
    "fullName": "Kerim Nišić",
    "description": "Kerim je budući web developer...",
    "location": "Novi Pazar, Serbia"
  },
  {
    "id": 17,
    "imageURL": "https://static.vecteezy.com/system/resources/thumbnails/005/544/718/small_2x/profile-icon-design-free-vector.jpg",
    "fullName": "Jusuf Selmanović",
    "description": "Jusuf je budući web developer...",
    "location": "Novi Pazar, Serbia"
  },
  {
    "id": 18,
    "imageURL": "https://static.vecteezy.com/system/resources/thumbnails/005/544/718/small_2x/profile-icon-design-free-vector.jpg",
    "fullName": "Hamza Iković",
    "description": "Hamza je budući web developer...",
    "location": "Novi Pazar, Serbia"
  },
  {
    "id": 19,
    "imageURL": "https://static.vecteezy.com/system/resources/thumbnails/005/544/718/small_2x/profile-icon-design-free-vector.jpg",
    "fullName": "Aleksandar Petrović",
    "description": "Aleksandar je budući web developer...",
    "location": "Novi Pazar, Serbia"
  },
  {
    "id": 20,
    "imageURL": "https://static.vecteezy.com/system/resources/thumbnails/005/544/718/small_2x/profile-icon-design-free-vector.jpg",
    "fullName": "Omer Dražanin",
    "description": "Omer je budući web developer...",
    "location": "Novi Pazar, Serbia"
  },
  {
    "id": 21,
    "imageURL": "https://static.vecteezy.com/system/resources/thumbnails/005/544/718/small_2x/profile-icon-design-free-vector.jpg",
    "fullName": "Abdulaziz Bešničanin",
    "description": "Abdulaziz je budući web developer...",
    "location": "Novi Pazar, Serbia"
  }
]
